melo_onnx/__init__.py
melo_onnx/commons.py
melo_onnx/hparams.py
melo_onnx/main.py
melo_onnx/text/__init__.py
melo_onnx/text/abstract_kernel.py
melo_onnx/text/bert_infer.py
melo_onnx/text/chinese_kernel.py
melo_onnx/text/chinese_mix_en_kernel.py
melo_onnx/text/cmudict_cache.pickle
melo_onnx/text/english_bert.py
melo_onnx/text/english_kernel.py
melo_onnx/text/japanese_kernel.py
melo_onnx/text/opencpop-strict.txt
melo_onnx/text/split_utils.py
melo_onnx/text/symbols.py
melo_onnx/text/tone_sandhi.py
melo_onnx/text/english_utils/__init__.py
melo_onnx/text/english_utils/abbreviations.py
melo_onnx/text/english_utils/number_norm.py
melo_onnx/text/english_utils/time_norm.py
melo_onnx/text/es_phonemizer/__init__.py
melo_onnx/text/es_phonemizer/base.py
melo_onnx/text/es_phonemizer/cleaner.py
melo_onnx/text/es_phonemizer/es_symbols.txt
melo_onnx/text/es_phonemizer/es_to_ipa.py
melo_onnx/text/es_phonemizer/example_ipa.txt
melo_onnx/text/es_phonemizer/gruut_wrapper.py
melo_onnx/text/es_phonemizer/punctuation.py
melo_onnx/text/es_phonemizer/spanish_symbols.txt
melo_onnx/text/fr_phonemizer/__init__.py
melo_onnx/text/fr_phonemizer/base.py
melo_onnx/text/fr_phonemizer/cleaner.py
melo_onnx/text/fr_phonemizer/example_ipa.txt
melo_onnx/text/fr_phonemizer/fr_to_ipa.py
melo_onnx/text/fr_phonemizer/french_abbreviations.py
melo_onnx/text/fr_phonemizer/french_symbols.txt
melo_onnx/text/fr_phonemizer/gruut_wrapper.py
melo_onnx/text/fr_phonemizer/punctuation.py
melotts_onnx-0.0.2.dist-info/LICENSE
melotts_onnx-0.0.2.dist-info/METADATA
melotts_onnx-0.0.2.dist-info/WHEEL
melotts_onnx-0.0.2.dist-info/top_level.txt
melotts_onnx-0.0.2.dist-info/RECORD
