Metadata-Version: 2.1
Name: melotts-onnx
Version: 0.0.2
Summary: An implementation of melo tts by onnxruntime
Author: Season Studio
Author-email: season-studio@outlook.com
License-File: LICENSE
Requires-Dist: certifi==2024.8.30
Requires-Dist: cffi==1.17.1
Requires-Dist: charset-normalizer==3.3.2
Requires-Dist: click==8.1.7
Requires-Dist: cn2an==0.5.22
Requires-Dist: colorama==0.4.6
Requires-Dist: coloredlogs==15.0.1
Requires-Dist: Distance==0.1.3
Requires-Dist: filelock==3.16.1
Requires-Dist: flatbuffers==24.3.25
Requires-Dist: fsspec==2024.9.0
Requires-Dist: g2p-en==2.1.0
Requires-Dist: huggingface-hub==0.25.1
Requires-Dist: humanfriendly==10.0
Requires-Dist: idna==3.10
Requires-Dist: inflect==7.4.0
Requires-Dist: jieba==0.42.1
Requires-Dist: joblib==1.4.2
Requires-Dist: more-itertools==10.5.0
Requires-Dist: mpmath==1.3.0
Requires-Dist: nltk==3.9.1
Requires-Dist: numpy==2.0.2
Requires-Dist: onnxruntime==1.19.2
Requires-Dist: openvino-telemetry==2024.1.0
Requires-Dist: packaging==24.1
Requires-Dist: proces==0.1.7
Requires-Dist: protobuf==5.28.2
Requires-Dist: pycparser==2.22
Requires-Dist: pypinyin==0.53.0
Requires-Dist: pyreadline3==3.5.4
Requires-Dist: PyYAML==6.0.2
Requires-Dist: regex==2024.9.11
Requires-Dist: requests==2.32.3
Requires-Dist: sympy==1.13.3
Requires-Dist: tokenizers==0.20.0
Requires-Dist: typeguard==4.3.0
Requires-Dist: typing-extensions==4.12.2
Requires-Dist: urllib3==2.2.3
